pybiosis/__init__.py
pybiosis/__main__.py
pybiosis/compiler.py
pybiosis/loader.py
pybiosis/applications/__init__.py
pybiosis/applications/monitors.py
pybiosis/applications/virtualdesktop.py
pybiosis/applications/ControlMyMonitor/ControlMyMonitor.exe
pybiosis/applications/VirtualDesktop/VirtualDesktop.exe
pybiosis-0.0.6.dist-info/LICENSE.txt
pybiosis-0.0.6.dist-info/METADATA
pybiosis-0.0.6.dist-info/WHEEL
pybiosis-0.0.6.dist-info/top_level.txt
pybiosis-0.0.6.dist-info/RECORD
