Metadata-Version: 2.1
Name: pybiosis
Version: 0.0.6
Summary: Python integration
Home-page: https://github.com/Palfore/Pybiosis
Author: Nawar Ismail
Author-email: nawar@palfore.com
License: UNKNOWN
Platform: UNKNOWN
Classifier: Programming Language :: Python :: 3
Classifier: License :: OSI Approved :: MIT License
Classifier: Operating System :: OS Independent
Requires-Python: >=3.6
